{
  "projects": [
    {
      "projectNumber": "PRJ-2025-001",
      "projectName": "Documentary Production",
      "description": "Documentary Production for Kabwe Communications Inc.",
      "projectType": 2,
      "status": 1,
      "customerId": 1,
      "customerName": "Kabwe Communications Inc.",
      "clientContact": "Malama Lungu",
      "startDate": "2024-10-04",
      "estimatedEndDate": "2025-04-23",
      "budgetedHours": 471,
      "budgetedCost": 2701592.68,
      "budgetedRevenue": 3869342.9,
      "actualHours": 58,
      "actualCost": 282721.2,
      "actualRevenue": 360526.19,
      "percentComplete": 13,
      "percentCompleteMethod": "Manual",
      "projectManagerName": "Nkole Bwalya",
      "projectLocation": "Lusaka",
      "city": "Lusaka"
    },
    {
      "projectNumber": "PRJ-2025-002",
      "projectName": "Radio Station Upgrade",
      "description": "Radio Station Upgrade for Ngosa Publishers Inc.",
      "projectType": 2,
      "status": 0,
      "customerId": 3,
      "customerName": "Ngosa Publishers Inc.",
      "clientContact": "Chisanga Zulu",
      "startDate": "2025-01-13",
      "estimatedEndDate": "2025-04-25",
      "budgetedHours": 152,
      "budgetedCost": 3170476.76,
      "budgetedRevenue": 4269495.5,
      "actualHours": 14,
      "actualCost": 297230.06,
      "actualRevenue": 421122.33,
      "percentComplete": 10,
      "percentCompleteMethod": "Manual",
      "projectManagerName": "Nakambwe Tembo",
      "projectLocation": "Mufulira",
      "city": "Mufulira"
    },
    {
      "projectNumber": "PRJ-2025-003",
      "projectName": "Newspaper Special Edition",
      "description": "Newspaper Special Edition for Tembo Media Co.",
      "projectType": 0,
      "status": 1,
      "customerId": 2,
      "customerName": "Tembo Media Co.",
      "clientContact": "Malama Phiri",
      "startDate": "2025-01-23",
      "estimatedEndDate": "2025-09-22",
      "budgetedHours": 344,
      "budgetedCost": 1209441.88,
      "budgetedRevenue": 1486792.56,
      "actualHours": 19,
      "actualCost": 79227.59,
      "actualRevenue": 73809.6,
      "percentComplete": 7,
      "percentCompleteMethod": "Manual",
      "projectManagerName": "Mwale Chanda",
      "projectLocation": "Kitwe",
      "city": "Kitwe"
    }
  ],
  "tasks": [
    {
      "projectNumber": "PRJ-2025-001",
      "taskName": "Planning & Design",
      "description": "Planning & Design \u2014 Documentary Production",
      "assignedTo": "Bwalya Zimba",
      "status": 2,
      "budgetedHours": 235,
      "actualHours": 23,
      "budgetedCost": 1237308.39,
      "actualCost": 145753.29,
      "startDate": "2024-10-10",
      "dueDate": "2024-10-30"
    },
    {
      "projectNumber": "PRJ-2025-001",
      "taskName": "Procurement & Setup",
      "description": "Procurement & Setup \u2014 Documentary Production",
      "assignedTo": "Nakambwe Mumba",
      "status": 1,
      "budgetedHours": 235,
      "actualHours": 23,
      "budgetedCost": 1175171.2,
      "actualCost": 133427.01,
      "startDate": "2024-10-25",
      "dueDate": "2024-12-06"
    },
    {
      "projectNumber": "PRJ-2025-002",
      "taskName": "Planning & Design",
      "description": "Planning & Design \u2014 Radio Station Upgrade",
      "assignedTo": "Nakambwe Mutale",
      "status": 3,
      "budgetedHours": 76,
      "actualHours": 5,
      "budgetedCost": 1299596.96,
      "actualCost": 128890.26,
      "startDate": "2025-01-18",
      "dueDate": "2025-02-02"
    },
    {
      "projectNumber": "PRJ-2025-002",
      "taskName": "Procurement & Setup",
      "description": "Procurement & Setup \u2014 Radio Station Upgrade",
      "assignedTo": "Zimba Chileshe",
      "status": 2,
      "budgetedHours": 76,
      "actualHours": 5,
      "budgetedCost": 1337966.15,
      "actualCost": 114434.88,
      "startDate": "2025-01-28",
      "dueDate": "2025-03-02"
    },
    {
      "projectNumber": "PRJ-2025-003",
      "taskName": "Planning & Design",
      "description": "Planning & Design \u2014 Newspaper Special Edition",
      "assignedTo": "Nkole Chanda",
      "status": 3,
      "budgetedHours": 172,
      "actualHours": 9,
      "budgetedCost": 507332.33,
      "actualCost": 32890.28,
      "startDate": "2025-01-27",
      "dueDate": "2025-02-28"
    },
    {
      "projectNumber": "PRJ-2025-003",
      "taskName": "Procurement & Setup",
      "description": "Procurement & Setup \u2014 Newspaper Special Edition",
      "assignedTo": "Kasonde Zimba",
      "status": 3,
      "budgetedHours": 172,
      "actualHours": 11,
      "budgetedCost": 695671.14,
      "actualCost": 45641.26,
      "startDate": "2025-02-12",
      "dueDate": "2025-03-26"
    }
  ],
  "expenses": [],
  "milestones": [],
  "invoices": []
}